dagster_hex/__init__.py
dagster_hex/assets.py
dagster_hex/consts.py
dagster_hex/ops.py
dagster_hex/resources.py
dagster_hex/types.py
dagster_hex-0.1.9.dist-info/METADATA
dagster_hex-0.1.9.dist-info/WHEEL
dagster_hex-0.1.9.dist-info/top_level.txt
dagster_hex-0.1.9.dist-info/RECORD
