Metadata-Version: 2.4
Name: dagster-hex
Version: 0.1.9
Summary: Dagster integration with Hex
Requires-Python: >=3.10
Requires-Dist: dagster>=1.3
Requires-Dist: requests>=2
